muji/__init__.py
muji/interpreter.py
muji/lexer.py
muji/main.py
muji/mukhya.py
muji/parser.py
muji/token_types.py
suddha_muji_bhasa-1.2.0.dist-info/METADATA
suddha_muji_bhasa-1.2.0.dist-info/WHEEL
suddha_muji_bhasa-1.2.0.dist-info/entry_points.txt
suddha_muji_bhasa-1.2.0.dist-info/top_level.txt
suddha_muji_bhasa-1.2.0.dist-info/RECORD
