Metadata-Version: 2.1
Name: suddha-muji-bhasa
Version: 1.2.0
Summary: Muji Programming Language Interpreter
Home-page: https://github.com/theSandeshStha/muji-bhasa
Author: Gulugulu Man
Author-email: guluguluman4@gmail.com
Classifier: Programming Language :: Python :: 3
Classifier: Operating System :: OS Independent
Requires-Python: >=3.6
